sequential_calibrationWithSA/__init__.py
sequential_calibrationWithSA/ex.py
sequential_calibrationWithSA/seqC.py
sequntial_calibrationWithSA/VSA.py
sequntial_calibrationWithSA/__init__.py
sequntial_calibrationWithSA/ex.py
sequential_calibrationWithSA-0.1.0.dist-info/METADATA
sequential_calibrationWithSA-0.1.0.dist-info/WHEEL
sequential_calibrationWithSA-0.1.0.dist-info/top_level.txt
sequential_calibrationWithSA-0.1.0.dist-info/RECORD
